autossl/__init__.py
autossl/__main__.py
autossl/__version__.py
autossl/credential.py
autossl/exception.py
autossl/manager.py
autossl/ssl.py
autossl/util.py
autossl/ca_manager/__init__.py
autossl/ca_manager/acme_v2_http01.py
autossl/ca_manager/base.py
autossl/ca_manager/local.py
autossl/server/__init__.py
autossl/server/base.py
autossl/server/incapsula.py
autossl/server/local.py
autossl/storage/__init__.py
autossl/storage/base.py
autossl/storage/gitscm.py
autossl/storage/local.py
autossl/tracking/__init__.py
autossl/tracking/base.py
autossl/tracking/local.py
tests/__init__.py
tests/test_ca_config.py
tests/test_command_line.py
tests/test_command_line_parser.py
tests/test_credentials.py
tests/test_manager.py
tests/test_ssl.py
tests/test_ssl_blueprint.py
tests/test_subca.py
tests/test_util.py
tests/util.py
tests/ca_manager/__init__.py
tests/ca_manager/test_base.py
tests/ca_manager/test_local.py
tests/server/__init__.py
tests/server/test_base.py
tests/server/test_incapsula.py
tests/server/test_local.py
tests/storage/__init__.py
tests/storage/test_base.py
tests/storage/test_gitscm.py
tests/storage/test_local.py
tests/tracking/__init__.py
tests/tracking/test_base.py
tests/tracking/test_local.py
autossl-0.9.7.dist-info/LICENSE
autossl-0.9.7.dist-info/METADATA
autossl-0.9.7.dist-info/WHEEL
autossl-0.9.7.dist-info/entry_points.txt
autossl-0.9.7.dist-info/top_level.txt
autossl-0.9.7.dist-info/RECORD
