Metadata-Version: 2.1
Name: autossl
Version: 0.9.7
Summary: SSL certificates monitoring, renewal and deployment.
Home-page: https://autossl.readthedocs.io
Author: Thibaud Castaing
Author-email: t-cas@users.noreply.github.com
License: MIT license
Platform: Unix; MacOS X
Classifier: Development Status :: 5 - Production/Stable
Classifier: Intended Audience :: Developers
Classifier: Natural Language :: English
Classifier: Topic :: Software Development
Classifier: Topic :: Software Development :: Libraries :: Python Modules
Classifier: License :: OSI Approved :: MIT License
Classifier: Operating System :: POSIX
Classifier: Operating System :: MacOS
Classifier: Programming Language :: Python
Classifier: Programming Language :: Python :: 3
Classifier: Programming Language :: Python :: 3.6
Classifier: Programming Language :: Python :: 3.7
Classifier: Programming Language :: Python :: 3.8
Classifier: Programming Language :: Python :: 3.9
License-File: LICENSE
Requires-Dist: six
Requires-Dist: cryptography
Requires-Dist: pyyaml
Requires-Dist: requests
Requires-Dist: enum34 ; python_version<"3.4"
Requires-Dist: pathlib2 ; python_version<"3.4"
Provides-Extra: acme
Requires-Dist: acme ; extra == 'acme'
Provides-Extra: all
Requires-Dist: GitPython ; extra == 'all'
Requires-Dist: acme ; extra == 'all'
Provides-Extra: git
Requires-Dist: GitPython ; extra == 'git'
